{
    "id": "jurnalarkeologi-89",
    "title": [
        "Back Cover Amerta Volume 34, Nomor 2, Tahun 2016"
    ],
    "creator": [
        "Puslit Arkenas, Redaksi"
    ],
    "format": [
        "application\/pdf"
    ],
    "source": [
        "AMERTA; Vol. 34 No. 2 (2016)",
        "2549-8908",
        "0215-1324"
    ],
    "publisher": [
        "Pusat Penelitian Arkeologi Nasional"
    ],
    "date": [
        "2016-12-30"
    ],
    "language": [
        "eng"
    ],
    "rights": [
        "Copyright (c) 2018 AMERTA"
    ],
    "relation": [
        "http:\/\/jurnalarkeologi.kemdikbud.go.id\/index.php\/amerta\/article\/view\/353\/218"
    ],
    "type": [
        "info:eu-repo\/semantics\/article",
        "info:eu-repo\/semantics\/publishedVersion"
    ]
}